MANIFEST.in
setup.cfg
setup.py
IOC_Parser.egg-info/PKG-INFO
IOC_Parser.egg-info/SOURCES.txt
IOC_Parser.egg-info/dependency_links.txt
IOC_Parser.egg-info/requires.txt
IOC_Parser.egg-info/top_level.txt
bin/iocp
ioc_parser.egg-info/SOURCES.txt
iocp/Output.py
iocp/Parser.py
iocp/Whitelist.py
iocp/__init__.py
iocp/data/patterns.ini
iocp/data/whitelists/whitelist_CVE.ini
iocp/data/whitelists/whitelist_Email.ini
iocp/data/whitelists/whitelist_Filename.ini
iocp/data/whitelists/whitelist_Filepath.ini
iocp/data/whitelists/whitelist_Host.ini
iocp/data/whitelists/whitelist_IP.ini
iocp/data/whitelists/whitelist_MD5.ini
iocp/data/whitelists/whitelist_Registry.ini
iocp/data/whitelists/whitelist_SHA1.ini
iocp/data/whitelists/whitelist_SHA256.ini
iocp/data/whitelists/whitelist_URL.ini