Metadata-Version: 1.1
Name: ioc-parser
Version: 0.9.1
Summary: Tool to extract indicators of compromise from security reports
Home-page: https://github.com/armbues/ioc_parser
Author: Armin Buescher
Author-email: armin.buescher@googlemail.com
License: MIT
Platform: UNKNOWN
Classifier: Development Status :: 4 - Beta
Classifier: Topic :: Security
Classifier: License :: OSI Approved :: MIT License
